src/__init__.py
src/app.py
src/cli.py
src/config.py
src/logger.py
src/main.py
src/api/__init__.py
src/api/dependencies.py
src/api/main.py
src/api/middleware/__init__.py
src/api/middleware/auth.py
src/api/middleware/rate_limit.py
src/api/routers/__init__.py
src/api/routers/health.py
src/api/routers/pose.py
src/api/routers/stream.py
src/api/websocket/__init__.py
src/api/websocket/connection_manager.py
src/api/websocket/pose_stream.py
src/commands/start.py
src/commands/status.py
src/commands/stop.py
src/config/__init__.py
src/config/domains.py
src/config/settings.py
src/core/__init__.py
src/core/csi_processor.py
src/core/phase_sanitizer.py
src/core/router_interface.py
src/database/connection.py
src/database/models.py
src/database/migrations/001_initial.py
src/database/migrations/env.py
src/hardware/__init__.py
src/hardware/csi_extractor.py
src/hardware/router_interface.py
src/middleware/auth.py
src/middleware/cors.py
src/middleware/error_handler.py
src/middleware/rate_limit.py
src/models/__init__.py
src/models/densepose_head.py
src/models/modality_translation.py
src/services/__init__.py
src/services/hardware_service.py
src/services/health_check.py
src/services/metrics.py
src/services/orchestrator.py
src/services/pose_service.py
src/services/stream_service.py
src/tasks/backup.py
src/tasks/cleanup.py
src/tasks/monitoring.py
wifi_densepose-1.1.0.dist-info/licenses/LICENSE
wifi_densepose-1.1.0.dist-info/METADATA
wifi_densepose-1.1.0.dist-info/WHEEL
wifi_densepose-1.1.0.dist-info/entry_points.txt
wifi_densepose-1.1.0.dist-info/top_level.txt
wifi_densepose-1.1.0.dist-info/RECORD
