Metadata-Version: 2.4
Name: wifi-densepose
Version: 1.1.0
Summary: WiFi-based human pose estimation using CSI data and DensePose neural networks
Home-page: https://github.com/ruvnet/wifi-densepose
Author: rUv
Author-email: rUv <ruv@ruv.net>
Maintainer: rUv
Maintainer-email: rUv <ruv@ruv.net>
License-Expression: MIT
Project-URL: Homepage, https://github.com/ruvnet/wifi-densepose
Project-URL: Documentation, https://github.com/ruvnet/wifi-densepose#readme
Project-URL: Repository, https://github.com/ruvnet/wifi-densepose.git
Project-URL: Bug Tracker, https://github.com/ruvnet/wifi-densepose/issues
Project-URL: Changelog, https://github.com/ruvnet/wifi-densepose/blob/main/CHANGELOG.md
Keywords: wifi,csi,pose-estimation,densepose,neural-networks,computer-vision,machine-learning,iot,wireless-sensing
Platform: any
Classifier: Development Status :: 4 - Beta
Classifier: Intended Audience :: Developers
Classifier: Intended Audience :: Science/Research
Classifier: Operating System :: OS Independent
Classifier: Programming Language :: Python :: 3
Classifier: Programming Language :: Python :: 3.9
Classifier: Programming Language :: Python :: 3.10
Classifier: Programming Language :: Python :: 3.11
Classifier: Programming Language :: Python :: 3.12
Classifier: Topic :: Scientific/Engineering :: Artificial Intelligence
Classifier: Topic :: Scientific/Engineering :: Image Processing
Classifier: Topic :: System :: Networking
Classifier: Topic :: Software Development :: Libraries :: Python Modules
Requires-Python: >=3.9
License-File: LICENSE
Requires-Dist: fastapi>=0.104.0
Requires-Dist: uvicorn[standard]>=0.24.0
Requires-Dist: pydantic>=2.5.0
Requires-Dist: pydantic-settings>=2.1.0
Requires-Dist: sqlalchemy>=2.0.0
Requires-Dist: alembic>=1.13.0
Requires-Dist: asyncpg>=0.29.0
Requires-Dist: psycopg2-binary>=2.9.0
Requires-Dist: redis>=5.0.0
Requires-Dist: aioredis>=2.0.0
Requires-Dist: torch>=2.1.0
Requires-Dist: torchvision>=0.16.0
Requires-Dist: numpy>=1.24.0
Requires-Dist: opencv-python>=4.8.0
Requires-Dist: pillow>=10.0.0
Requires-Dist: scikit-learn>=1.3.0
Requires-Dist: scipy>=1.11.0
Requires-Dist: matplotlib>=3.7.0
Requires-Dist: pandas>=2.1.0
Requires-Dist: scapy>=2.5.0
Requires-Dist: pyserial>=3.5
Requires-Dist: paramiko>=3.3.0
Requires-Dist: click>=8.1.0
Requires-Dist: rich>=13.6.0
Requires-Dist: typer>=0.9.0
Requires-Dist: python-multipart>=0.0.6
Requires-Dist: python-jose[cryptography]>=3.3.0
Requires-Dist: passlib[bcrypt]>=1.7.4
Requires-Dist: python-dotenv>=1.0.0
Requires-Dist: pyyaml>=6.0
Requires-Dist: toml>=0.10.2
Requires-Dist: prometheus-client>=0.19.0
Requires-Dist: structlog>=23.2.0
Requires-Dist: psutil>=5.9.0
Requires-Dist: httpx>=0.25.0
Requires-Dist: aiofiles>=23.2.0
Requires-Dist: marshmallow>=3.20.0
Requires-Dist: jsonschema>=4.19.0
Requires-Dist: celery>=5.3.0
Requires-Dist: kombu>=5.3.0
Requires-Dist: pytest>=7.4.0
Requires-Dist: pytest-asyncio>=0.21.0
Requires-Dist: pytest-cov>=4.1.0
Requires-Dist: black>=23.9.0
Requires-Dist: isort>=5.12.0
Requires-Dist: flake8>=6.1.0
Requires-Dist: mypy>=1.6.0
Provides-Extra: dev
Requires-Dist: pytest>=7.4.0; extra == "dev"
Requires-Dist: pytest-asyncio>=0.21.0; extra == "dev"
Requires-Dist: pytest-cov>=4.1.0; extra == "dev"
Requires-Dist: pytest-mock>=3.12.0; extra == "dev"
Requires-Dist: pytest-xdist>=3.3.0; extra == "dev"
Requires-Dist: black>=23.9.0; extra == "dev"
Requires-Dist: isort>=5.12.0; extra == "dev"
Requires-Dist: flake8>=6.1.0; extra == "dev"
Requires-Dist: mypy>=1.6.0; extra == "dev"
Requires-Dist: pre-commit>=3.5.0; extra == "dev"
Requires-Dist: bandit>=1.7.0; extra == "dev"
Requires-Dist: safety>=2.3.0; extra == "dev"
Provides-Extra: docs
Requires-Dist: sphinx>=7.2.0; extra == "docs"
Requires-Dist: sphinx-rtd-theme>=1.3.0; extra == "docs"
Requires-Dist: sphinx-autodoc-typehints>=1.25.0; extra == "docs"
Requires-Dist: myst-parser>=2.0.0; extra == "docs"
Provides-Extra: gpu
Requires-Dist: torch>=2.1.0; extra == "gpu"
Requires-Dist: torchvision>=0.16.0; extra == "gpu"
Requires-Dist: nvidia-ml-py>=12.535.0; extra == "gpu"
Provides-Extra: monitoring
Requires-Dist: grafana-api>=1.0.3; extra == "monitoring"
Requires-Dist: influxdb-client>=1.38.0; extra == "monitoring"
Requires-Dist: elasticsearch>=8.10.0; extra == "monitoring"
Provides-Extra: deployment
Requires-Dist: gunicorn>=21.2.0; extra == "deployment"
Requires-Dist: docker>=6.1.0; extra == "deployment"
Requires-Dist: kubernetes>=28.1.0; extra == "deployment"
Dynamic: author
Dynamic: home-page
Dynamic: license-file
Dynamic: maintainer
Dynamic: platform
Dynamic: requires-python
